impact_uka-0.0.2.dist-info/licenses/LICENSE
uka/__init__.py
uka/karmi/__init__.py
uka/karmi/rmi/__init__.py
uka/karmi/rmi/remote_exception.py
uka/karmi/rmi/server/__init__.py
uka/karmi/rmi/server/remote_stub.py
uka/karmi/rmi/server/replicated_object.py
uka/karo/__init__.py
uka/karo/replica_statistics.py
uka/patch/__init__.py
uka/patch/patch_input.py
uka/patch/patch_output.py
uka/patch/patchable.py
uka/patch/patchable_root.py
uka/patch/reference_filter.py
uka/transport/__init__.py
uka/transport/basic_io.py
uka/transport/deep_clone.py
uka/transport/marshal_stream.py
uka/transport/transport_descriptor.py
uka/transport/transportable.py
uka/transport/unmarshal_stream.py
uka/transport/value_io.py
uka/util/__init__.py
uka/util/printable.py
uka/util/to_string.py
impact_uka-0.0.2.dist-info/METADATA
impact_uka-0.0.2.dist-info/WHEEL
impact_uka-0.0.2.dist-info/top_level.txt
impact_uka-0.0.2.dist-info/RECORD
