Metadata-Version: 2.4
Name: impact-uka
Version: 0.0.2
Summary: This is a Python reimplementation of the Java uka package utilized in the original Imapct Java application - https://sourceforge.net/projects/impact/
Author-email: Peter Harding <plh@performiq.com>
License:                     GNU GENERAL PUBLIC LICENSE
Project-URL: Homepage, https://gitlab.com/impact-analysis/impact-uka
Project-URL: Repository, https://gitlab.com/impact-analysis/impact-uka
Classifier: Programming Language :: Python :: 3
Classifier: Programming Language :: Python :: 3 :: Only
Classifier: License :: OSI Approved :: GNU General Public License v2 (GPLv2)
Classifier: Operating System :: OS Independent
Requires-Python: >=3.10
License-File: LICENSE
Provides-Extra: test
Requires-Dist: pytest>=8; extra == "test"
Dynamic: license-file
